t3dn_sdk_blender/__init__.py
t3dn_sdk_blender/addon_update_service.py
t3dn_sdk_blender/queue.py
t3dn_sdk_blender/ui.py
t3dn_sdk_core/__init__.py
t3dn_sdk_core/api/__init__.py
t3dn_sdk_core/api/base_api.py
t3dn_sdk_core/api/purchase_tracker.py
t3dn_sdk_core/api/update.py
t3dn_sdk_core/exceptions/__init__.py
t3dn_sdk_core/exceptions/api_exception.py
t3dn_sdk_core/models/__init__.py
t3dn_sdk_core/models/purchase_tracker.py
t3dn_sdk_core/services/__init__.py
t3dn_sdk_core/services/update_service.py
t3dn_sdk_core/services/purchase_tracker/__init__.py
t3dn_sdk_core/services/purchase_tracker/download.py
t3dn_sdk_core/services/purchase_tracker/install.py
t3dn_sdk_core/services/purchase_tracker/purchase.py
t3dn_sdk_core/services/purchase_tracker/service.py
t3dn_sdk_core/utils/__init__.py
t3dn_sdk_core/utils/config.py
t3dn_sdk_core/utils/decorators.py
t3dn_sdk_core/utils/purchase_tracker.py
t3dn_sdk_core/utils/session_store.py
t3dn_sdk_core/utils/browser/__init__.py
t3dn_sdk_core/utils/browser/__main__.py
t3dn_sdk_core/utils/browser/macos.py
t3dn_sdk_core/utils/browser/webserver.py
t3dn_sdk_core/utils/browser/windows.py
t3dn_sdk_core/utils/browser/x11/__init__.py
t3dn_sdk_core/utils/browser/x11/xrandr.py
t3dn_sdk_core/utils/focus/__init__.py
t3dn_sdk_core/utils/focus/macos.py
t3dn_sdk_core/utils/focus/windows.py
t3dn_sdk_core/utils/focus/x11.py
t3dn_sdk-0.1.2.dist-info/METADATA
t3dn_sdk-0.1.2.dist-info/WHEEL
t3dn_sdk-0.1.2.dist-info/top_level.txt
t3dn_sdk-0.1.2.dist-info/RECORD
